http_server_pytest_fixtures/fixtures.py
http_server_pytest_fixtures/gencert.sh
http_server_pytest_fixtures-0.0.2.dist-info/METADATA
http_server_pytest_fixtures-0.0.2.dist-info/WHEEL
http_server_pytest_fixtures-0.0.2.dist-info/entry_points.txt
http_server_pytest_fixtures-0.0.2.dist-info/top_level.txt
http_server_pytest_fixtures-0.0.2.dist-info/RECORD
